MANIFEST.in
README.rst
setup.py
3rd/steap_api/steap_api.lib
3rd/steap_api/steap_control_api.h
include/defines.h
include/device_control_module.h
include/exceptions.h
include/object_steap_device.h
slthost/__init__.py
slthost.egg-info/PKG-INFO
slthost.egg-info/SOURCES.txt
slthost.egg-info/dependency_links.txt
slthost.egg-info/top_level.txt
slthost/../../../pcsteap/steap_api/steap_control_api.h
slthost/../../../pcsteap/steap_api/x64/Release/steap_api.lib
src/device_control_module.cpp
src/exceptions.cpp
src/object_steap_device.cpp