Metadata-Version: 2.1
Name: slthost
Version: 1.1
Summary: Library for interfacing with Sealta devices in Python
Home-page: UNKNOWN
Author: yufan
Author-email: 1014720522@qq.com
Maintainer: yufan
Maintainer-email: 1014720522@qq.com
License: MIT
Platform: UNKNOWN
Classifier: Programming Language :: Python :: 3
Classifier: Programming Language :: Python :: 3.6
Classifier: Programming Language :: Python :: 3.7
Classifier: Programming Language :: Python :: 3.8
Classifier: Programming Language :: Python :: 3.9
Classifier: Programming Language :: Python :: 3.10
Classifier: Programming Language :: Python :: 3.11
